[
  {
    "id": "clip002",
    "title": "Sultan Alp Arslan",
    "embed": "https://rumble.com/embed/v6z8qve/?pub=4noco6",
    "thumb": "thumbs/alp-arslan.jpg",
    "desc": "Short highlight: Sultan Alp Arslan.",
    "added": "2025-11-08T09:20:00Z",
    "watchUrl": "https://www.smtvurdu.site/series?series=alp-arslan",
    "likes": 0,
    "comments": 0,
    "shares": 0
  },
  {
    "id": "clip001",
    "title": "Sultan Murad",
    "embed": "https://rumble.com/embed/v6z8qse/?pub=4noco6",
    "thumb": "thumbs/murad.jpg",
    "desc": "Short highlight: Sultan Murad.",
    "added": "2025-11-07T18:00:00Z",
    "watchUrl": "https://www.smtvurdu.site/series?series=sultan-mehmet-fatih",
    "likes": 0,
    "comments": 0,
    "shares": 0
  },
  {
    "id": "clip003",
    "title": "Kurulus Orhan",
    "embed": "https://rumble.com/embed/v6zb1f8/?pub=4noco6",
    "thumb": "thumbs/murad.jpg",
    "desc": "Orhan Bolum 3 Trailer 2",
    "added": "2025-11-10T18:00:00Z",
    "watchUrl": "https://www.smtvurdu.site/series?series=kurulus-orhan-ur",
    "likes": 879,
    "comments": 0,
    "shares": 367
  }
]
